aind_tars_service_client/__init__.py
aind_tars_service_client/api_client.py
aind_tars_service_client/api_response.py
aind_tars_service_client/configuration.py
aind_tars_service_client/exceptions.py
aind_tars_service_client/py.typed
aind_tars_service_client/rest.py
aind_tars_service_client/api/__init__.py
aind_tars_service_client/api/default_api.py
aind_tars_service_client/api/healthcheck_api.py
aind_tars_service_client/models/__init__.py
aind_tars_service_client/models/alias.py
aind_tars_service_client/models/health_check.py
aind_tars_service_client/models/http_validation_error.py
aind_tars_service_client/models/molecule_data.py
aind_tars_service_client/models/molecule_type.py
aind_tars_service_client/models/prep_lot_data.py
aind_tars_service_client/models/species.py
aind_tars_service_client/models/targeted_cell_population.py
aind_tars_service_client/models/targeted_roi.py
aind_tars_service_client/models/titers.py
aind_tars_service_client/models/validation_error.py
aind_tars_service_client/models/validation_error_loc_inner.py
aind_tars_service_client/models/viral_prep.py
aind_tars_service_client/models/viral_prep_type.py
aind_tars_service_client/models/virus_data.py
aind_tars_service_client-0.1.3.dist-info/METADATA
aind_tars_service_client-0.1.3.dist-info/WHEEL
aind_tars_service_client-0.1.3.dist-info/top_level.txt
aind_tars_service_client-0.1.3.dist-info/RECORD
